pirev/__init__.py
pirev/__main__.py
pirev/cpuinfo.py
pirev/manufacturer.py
pirev/memory.py
pirev/newrev.py
pirev/oldrev.py
pirev/pirev.py
pirev/processor.py
pirev/revinfo.py
pirev/type.py
pirev-1.2.1.dist-info/LICENSE
pirev-1.2.1.dist-info/METADATA
pirev-1.2.1.dist-info/WHEEL
pirev-1.2.1.dist-info/top_level.txt
pirev-1.2.1.dist-info/RECORD
