Metadata-Version: 2.1
Name: pirev
Version: 1.2.1
Summary: Raspberry Pi revision utility
Home-page: https://github.com/samjrdn/pirev-python
Author: Sam Jordan
Author-email: sam@jrdn.ca
License: UNKNOWN
Platform: UNKNOWN
Classifier: Programming Language :: Python :: 3
Classifier: License :: OSI Approved :: MIT License
Classifier: Operating System :: OS Independent
